Compiled from "Main.java"
public class Main {
  public Main();
    descriptor: ()V
    Code:
       0: aload_0
       1: invokespecial #1                  // Method java/lang/Object."<init>":()V
       4: return

  public static void bubbleSort(int[]);
    descriptor: ([I)V
    Code:
       0: aload_0	//zaladuj referencje na stos ze zmiennej lokalnej 0
       1: arraylength	//pobierz dlugosc tablicy
       2: istore_1	//przechowaj wartosc int do zmiennej 1
       3: iconst_0	//zaladuj wartosc int 0 na stos
       4: istore_2	//przechowaj wartosc int do zmiennej 2
       5: iload_2	//zaladuj wartoc int do zmiennej lokalnej 2
       6: iload_1	//to samo tylko do zmiennej lokalnej 1
       7: iconst_1	//zaladuj wartosc int 1 na stos
       8: isub		//odejmij int
       9: if_icmpge     66 //jesli wartosc1 jest wieksza lub rowna //					wartosci2 utworz rozgalezienie do instrukcji w branchoffset
      12: iconst_0	
      13: istore_3	//przechowaj wartosc int do zmiennej 3
      14: iload_3	//zaladuj wartosc int do zmiennej 3
      15: iload_1	//to samo tylko do zmiennej 1
      16: iload_2	//to samo tylko do zmiennej 2
      17: isub
      18: iconst_1
      19: isub
      20: if_icmpge     60
      23: aload_0
      24: iload_3
      25: iaload	//zaladuj int z tablicy
      26: aload_0
      27: iload_3
      28: iconst_1
      29: iadd		//dodaj dwa inty
      30: iaload
      31: if_icmple     54 //jesli wartosc1 jest mniejsza lub rowna wartosc2, utworz rozgalezienie do instrukcji w branchoffset
      34: aload_0
      35: iload_3
      36: iaload
      37: istore        4 //przechowaj wartosc int w zmiennej #index
      39: aload_0
      40: iload_3
      41: aload_0
      42: iload_3
      43: iconst_1
      44: iadd
      45: iaload
      46: iastore
      47: aload_0
      48: iload_3
      49: iconst_1
      50: iadd
      51: iload         4
      53: iastore
      54: iinc          3, 1 //inkrementuj zmienna lokalna #index o staly bajt
      57: goto          14 //przechodzi do kolejnej instrukcji w branchoffset
      60: iinc          2, 1
      63: goto          5
      66: return	//zwroc void z metody

  public static void main(java.lang.String[]);
    descriptor: ([Ljava/lang/String;)V
    Code:
       0: bipush        8 //umiesc bajt na stosie jako wartosc int
       2: newarray       int //utworz nowa tablice
       4: dup		//powiel wartosc na szczycie stosu
       5: iconst_0
       6: iconst_4	//zaladuj wartosc int 4 na stos
       7: iastore
       8: dup
       9: iconst_1
      10: iconst_3
      11: iastore
      12: dup
      13: iconst_2
      14: bipush        7
      16: iastore
      17: dup
      18: iconst_3
      19: bipush        8
      21: iastore
      22: dup
      23: iconst_4
      24: bipush        53
      26: iastore
      27: dup
      28: iconst_5		//zaladuj wartosc int 5 na stos
      29: bipush        6
      31: iastore
      32: dup
      33: bipush        6
      35: iconst_5
      36: iastore
      37: dup
      38: bipush        7
      40: iconst_2
      41: iastore
      42: astore_1		//przechowaj referencje w zmiennej lokalnej 1
      43: getstatic     #2     //odczytaj wartosc statycznego pola klasy, gdzie pole jest zidentyfikowane poprzez referencje pola             // Field java/lang/System.out:Ljava/io/PrintStream;
      46: aload_1
      47: invokestatic  #3      //wywolaj metode statyczna i umiesc wynik na stosie            // Method java/util/Arrays.toString:([I)Ljava/lang/String;
      50: invokedynamic #4,  0  //wywolaj metode dynamiczna i umiesc wynik na stosie           // InvokeDynamic #0:makeConcatWithConstants:(Ljava/lang/String;)Ljava/lang/String;
      55: invokevirtual #5       //wywolaj metode wirtualna i umiesc wynik na stosie           // Method java/io/PrintStream.println:(Ljava/lang/String;)V
      58: aload_1
      59: invokestatic  #6                  // Method bubbleSort:([I)V
      62: getstatic     #2    //odczytaj wartosc statycznego pola klasy              // Field java/lang/System.out:Ljava/io/PrintStream;
      65: aload_1
      66: invokestatic  #3                  // Method java/util/Arrays.toString:([I)Ljava/lang/String;
      69: invokedynamic #7,  0              // InvokeDynamic #1:makeConcatWithConstants:(Ljava/lang/String;)Ljava/lang/String;
      74: invokevirtual #5                  // Method java/io/PrintStream.println:(Ljava/lang/String;)V
      77: return
}
